colorThis/__init__.py
colorThis/colorThis.py
colorThis-1.1.2.dist-info/DESCRIPTION.rst
colorThis-1.1.2.dist-info/METADATA
colorThis-1.1.2.dist-info/RECORD
colorThis-1.1.2.dist-info/WHEEL
colorThis-1.1.2.dist-info/entry_points.txt
colorThis-1.1.2.dist-info/metadata.json
colorThis-1.1.2.dist-info/top_level.txt
