Metadata-Version: 2.0
Name: colorThis
Version: 1.1.2
Summary: allows for various methods of creating coloured text output in terminal
Home-page: https://github.com/DrTexxOfficial/colorThis
Author: Denver Pallis
Author-email: UNKNOWN
License: UNKNOWN
Project-URL: Bug Reports, https://github.com/DrTexxOfficial/colorThis/issues
Project-URL: Source, https://github.com/DrTexxOfficial/colorThis/
Requires-Dist: colorama
